flake8_complicated_walrus.py
flake8_complicated_walrus-2.1.0.dist-info/LICENSE
flake8_complicated_walrus-2.1.0.dist-info/METADATA
flake8_complicated_walrus-2.1.0.dist-info/WHEEL
flake8_complicated_walrus-2.1.0.dist-info/entry_points.txt
flake8_complicated_walrus-2.1.0.dist-info/RECORD
