Metadata-Version: 2.1
Name: flake8-complicated-walrus
Version: 2.1.0
Summary: This Flake8 plugin for checking complicated assignment expressions.
Home-page: https://github.com/DDmitiy/flake8-complicated-walrus
License: MIT
Keywords: flake8-complicated-walrus,flake8,plugin,walrus,assignment expression,if,conditions
Author: Dudov Dmitry
Author-email: dudov.dm@gmail.com
Requires-Python: >=3.9,<4.0
Classifier: Framework :: Flake8
Classifier: License :: OSI Approved :: MIT License
Classifier: Programming Language :: Python
Classifier: Programming Language :: Python :: 3
Classifier: Programming Language :: Python :: 3.9
Classifier: Programming Language :: Python :: 3.10
Classifier: Programming Language :: Python :: 3.11
Classifier: Topic :: Software Development :: Libraries :: Python Modules
Classifier: Topic :: Software Development :: Quality Assurance
Requires-Dist: astpretty (>=3.0,<4.0)
Requires-Dist: flake8
Project-URL: Repository, https://github.com/DDmitiy/flake8-complicated-walrus
